{
  "version": 2,
  "extractor": "pdffigures2",
  "figures": [
    {
      "url": "assets/figures/arxiv/2605.12145v2/fig-001.webp",
      "caption": "Table 1. AV setting: comparison with state-of-the-art methods on (i) event classification (AVE, Precision) and (ii) event localization (AVVP, Segment-level Accuracy). V→A / A→V denote transfer directions.",
      "page": 7,
      "index": 1,
      "width": 618,
      "height": 197
    },
    {
      "url": "assets/figures/arxiv/2605.12145v2/fig-002.webp",
      "caption": "Figure 2. The overview of our proposed CoDAAR framework. (a) Model architecture. (b) The Cross-modal Discrete Alignment mechanism, comprising Discrete Temporal Alignment (DTA), CPC loss, Cascading Semantic Alignment (CSA), and commitment loss.",
      "page": 3,
      "index": 2,
      "width": 994,
      "height": 368
    },
    {
      "url": "assets/figures/arxiv/2605.12145v2/fig-003.webp",
      "caption": "Figure 6. Cross-modal Discrete Alignment Framework",
      "page": 13,
      "index": 3,
      "width": 688,
      "height": 431
    }
  ]
}